<annotation>
	<folder>soju</folder>
	<filename>soju_0266.jpg</filename>
	<path>refri_dataset/train/images/soju_0266.jpg</path>
	<source>
		<database>Unknown</database>
	</source>
	<size>
		<width>359</width>
		<height>359</height>
		<depth>3</depth>
	</size>
	<segmented>0</segmented>
	<object>
		<name>soju</name>
		<pose>Unspecified</pose>
		<truncated>0</truncated>
		<difficult>0</difficult>
		<bndbox>
			<xmin>3</xmin>
			<ymin>6</ymin>
			<xmax>107</xmax>
			<ymax>256</ymax>
		</bndbox>
	</object>
	<object>
		<name>soju</name>
		<pose>Unspecified</pose>
		<truncated>0</truncated>
		<difficult>0</difficult>
		<bndbox>
			<xmin>144</xmin>
			<ymin>29</ymin>
			<xmax>279</xmax>
			<ymax>175</ymax>
		</bndbox>
	</object>
</annotation>
